devopsai/_version.py
devopsai/cli.py
devopsai/config.py
devopsai/core.py
devopsai/version.py
devopsAI-0.1.5.dist-info/LICENCE
devopsAI-0.1.5.dist-info/METADATA
devopsAI-0.1.5.dist-info/WHEEL
devopsAI-0.1.5.dist-info/entry_points.txt
devopsAI-0.1.5.dist-info/top_level.txt
devopsAI-0.1.5.dist-info/RECORD
