Metadata-Version: 2.2
Name: devopsAI
Version: 0.1.5
Summary: A utility for executing system commands via AI Agent
Author-email: Dineshkanna <kannadinesh.m@gmail.com>
License: SQUAPL
Project-URL: Homepage, https://github.com/Dineshkanna654/devops
Project-URL: Bug Tracker, https://github.com/Dineshkanna654/devops/issues
Classifier: Programming Language :: Python :: 3
Classifier: License :: Other/Proprietary License
Classifier: Operating System :: OS Independent
Requires-Python: >=3.12
License-File: LICENCE
Requires-Dist: requests>=2.25.0
